DemoTestUnit/__init__.py
DemoTestUnit/capabilities/__init__.py
DemoTestUnit/plots/__init__.py
DemoTestUnit/scores/__init__.py
DemoTestUnit/tests/__init__.py
DemoTestUnit-1.2.0.dist-info/DESCRIPTION.rst
DemoTestUnit-1.2.0.dist-info/METADATA
DemoTestUnit-1.2.0.dist-info/RECORD
DemoTestUnit-1.2.0.dist-info/WHEEL
DemoTestUnit-1.2.0.dist-info/metadata.json
DemoTestUnit-1.2.0.dist-info/top_level.txt
